set_git_hooks_dir/__init__.py
set_git_hooks_dir-0.0.3.dist-info/METADATA
set_git_hooks_dir-0.0.3.dist-info/WHEEL
set_git_hooks_dir-0.0.3.dist-info/top_level.txt
set_git_hooks_dir-0.0.3.dist-info/RECORD
